srtcleaner/__about__.py
srtcleaner/__init__.py
srtcleaner/__main__.py
srtcleaner/apppaths.py
srtcleaner/srtcleaner.py
srtcleaner/data/README.conf.txt
srtcleaner/data/nautilus-script.sh
srtcleaner/data/srtcleaner.template.conf
srtcleaner-1.1.1.dist-info/LICENSE
srtcleaner-1.1.1.dist-info/METADATA
srtcleaner-1.1.1.dist-info/WHEEL
srtcleaner-1.1.1.dist-info/entry_points.txt
srtcleaner-1.1.1.dist-info/top_level.txt
srtcleaner-1.1.1.dist-info/RECORD
