Metadata-Version: 2.1
Name: srtcleaner
Version: 1.1.1
Summary: Clean up SRT subtitle files removing ads and misplaced credits.
Home-page: https://github.com/MestreLion/srtcleaner
Author: Rodrigo Silva (MestreLion)
Author-email: linux@rodrigosilva.com
License: GPLv3+
Project-URL: Bug Tracker, https://github.com/MestreLion/srtcleaner/issues
Project-URL: Source Code, https://github.com/MestreLion/srtcleaner
Keywords: subtitles srt library
Platform: UNKNOWN
Classifier: Development Status :: 5 - Production/Stable
Classifier: Environment :: Console
Classifier: Intended Audience :: Developers
Classifier: Intended Audience :: End Users/Desktop
Classifier: License :: DFSG approved
Classifier: License :: OSI Approved :: GNU General Public License v3 or later (GPLv3+)
Classifier: Natural Language :: English
Classifier: Operating System :: OS Independent
Classifier: Programming Language :: Python :: 2
Classifier: Programming Language :: Python :: 2.7
Classifier: Programming Language :: Python :: 3
Classifier: Programming Language :: Python :: 3.4
Classifier: Programming Language :: Python :: 3.5
Classifier: Programming Language :: Python :: 3.6
Classifier: Programming Language :: Python :: 3.7
Classifier: Programming Language :: Python :: 3.8
Classifier: Programming Language :: Python :: 3.9
Classifier: Programming Language :: Python :: 3.10
Classifier: Topic :: Software Development :: Libraries :: Python Modules
Classifier: Topic :: Multimedia :: Video
Classifier: Topic :: Text Processing
Classifier: Topic :: Utilities
Requires-Python: >=2.7
Requires-Dist: pysrt
Requires-Dist: file-magic
